lycoris/__init__.py
lycoris-0.0.0.dist-info/LICENSE
lycoris-0.0.0.dist-info/METADATA
lycoris-0.0.0.dist-info/WHEEL
lycoris-0.0.0.dist-info/top_level.txt
lycoris-0.0.0.dist-info/RECORD
