Metadata-Version: 2.1
Name: lycoris
Version: 0.0.0
Summary: Lycoris
Home-page: https://github.com/demianoh/lycoris
Author: Demian Oh
Author-email: demie.oh@gmail.com
Classifier: License :: OSI Approved :: MIT License
Classifier: Operating System :: OS Independent
Classifier: Programming Language :: Python :: 3
Requires-Python: >=3.10
License-File: LICENSE
